wagtailfontawesome/__init__.py
wagtailfontawesome/blocks.py
wagtailfontawesome/wagtail_hooks.py
wagtailfontawesome/static/wagtailfontawesome/css/fontawesome.css
wagtailfontawesome/static/wagtailfontawesome/css/fontawesome.css.gz
wagtailfontawesome/static/wagtailfontawesome/css/wagtailfontawesome.css
wagtailfontawesome/static/wagtailfontawesome/css/wagtailfontawesome.css.gz
wagtailfontawesome/static/wagtailfontawesome/fonts/FontAwesome.otf
wagtailfontawesome/static/wagtailfontawesome/fonts/fontawesome-webfont.eot
wagtailfontawesome/static/wagtailfontawesome/fonts/fontawesome-webfont.svg
wagtailfontawesome/static/wagtailfontawesome/fonts/fontawesome-webfont.ttf
wagtailfontawesome/static/wagtailfontawesome/fonts/fontawesome-webfont.woff
wagtailfontawesome/static/wagtailfontawesome/fonts/fontawesome-webfont.woff2
wagtailfontawesome/templates/wagtailfontawesome/blocks/icon.html
wagtailfontawesome/templatetags/__init__.py
wagtailfontawesome/templatetags/wagtailfontawesome.py
wagtailfontawesome-1.2.1.dist-info/DESCRIPTION.rst
wagtailfontawesome-1.2.1.dist-info/METADATA
wagtailfontawesome-1.2.1.dist-info/RECORD
wagtailfontawesome-1.2.1.dist-info/WHEEL
wagtailfontawesome-1.2.1.dist-info/metadata.json
wagtailfontawesome-1.2.1.dist-info/top_level.txt
