Metadata-Version: 1.1
Name: wagtailfontawesome
Version: 1.2.1
Summary: Add FontAwesome icons to StreamField.
Home-page: https://gitlab.com/alexgleason/wagtailfontawesome
Author: Alex Gleason
Author-email: alex@alexgleason.me
License: MIT
Keywords: development
Platform: UNKNOWN
Classifier: Environment :: Web Environment
Classifier: Framework :: Django
Classifier: Intended Audience :: Developers
Classifier: Operating System :: OS Independent
Classifier: Programming Language :: Python
Classifier: Programming Language :: Python :: 3
Classifier: Topic :: Internet :: WWW/HTTP
Classifier: Topic :: Internet :: WWW/HTTP :: Dynamic Content
